{
    "users" : [
        {
            "accountName"   : "User",
            "displayName"   : "1",
            "email"         : "email@sample"
        },
        {
            "accountName"   : "User",
            "displayName"   : "2",
            "email"         : "email@sample"
        },
        {
            "accountName"   : "User",
            "displayName"   : "3",
            "email"         : "email@sample"
        },
        {
            "accountName"   : "User",
            "displayName"   : "4",
            "email"         : "email@sample"
        },
        {
            "accountName"   : "User",
            "displayName"   : "5",
            "email"         : "email@sample"
        },
        {
            "accountName"   : "User",
            "displayName"   : "6",
            "email"         : "email@sample"
        },
        {
            "accountName"   : "User",
            "displayName"   : "7",
            "email"         : "email@sample"
        },
        {
            "accountName"   : "User",
            "displayName"   : "8",
            "email"         : "email@sample"
        },
        {
            "accountName"   : "User",
            "displayName"   : "9",
            "email"         : "email@sample"
        },
        {
            "accountName"   : "User",
            "displayName"   : "10",
            "email"         : "email@sample"
        },
        {
            "accountName"   : "User",
            "displayName"   : "11",
            "email"         : "email@sample"
        },
        {
            "accountName"   : "User",
            "displayName"   : "12",
            "email"         : "email@sample"
        },
        {
            "accountName"   : "User",
            "displayName"   : "13",
            "email"         : "email@sample"
        },
        {
            "accountName"   : "User",
            "displayName"   : "14",
            "email"         : "email@sample"
        },
        {
            "accountName"   : "User",
            "displayName"   : "15",
            "email"         : "email@sample"
        },
        {
            "accountName"   : "User",
            "displayName"   : "16",
            "email"         : "email@sample"
        },
        {
            "accountName"   : "User",
            "displayName"   : "17",
            "email"         : "email@sample"
        },
        {
            "accountName"   : "User",
            "displayName"   : "18",
            "email"         : "email@sample"
        },
        {
            "accountName"   : "User",
            "displayName"   : "19",
            "email"         : "email@sample"
        },
        {
            "accountName"   : "User",
            "displayName"   : "20",
            "email"         : "email@sample"
        },
        {
            "accountName"   : "User",
            "displayName"   : "21",
            "email"         : "email@sample"
        },
        {
            "accountName"   : "User",
            "displayName"   : "22",
            "email"         : "email@sample"
        },
        {
            "accountName"   : "User",
            "displayName"   : "23",
            "email"         : "email@sample"
        },
        {
            "accountName"   : "User",
            "displayName"   : "24",
            "email"         : "email@sample"
        },
        {
            "accountName"   : "User",
            "displayName"   : "25",
            "email"         : "email@sample"
        },
        {
            "accountName"   : "User",
            "displayName"   : "26",
            "email"         : "email@sample"
        },
        {
            "accountName"   : "User",
            "displayName"   : "27",
            "email"         : "email@sample"
        },
        {
            "accountName"   : "User",
            "displayName"   : "28",
            "email"         : "email@sample"
        }
    ]
}